evalrag/__init__.py
evalrag/evaluator.py
evalrag/utils.py
evalrag/metrics/__init__.py
evalrag/metrics/hallucination.py
evalrag/metrics/mrr.py
evalrag/metrics/precision.py
evalrag/metrics/recall.py
evalrag/metrics/similarity.py
benchlite-0.1.1.dist-info/METADATA
benchlite-0.1.1.dist-info/WHEEL
benchlite-0.1.1.dist-info/top_level.txt
benchlite-0.1.1.dist-info/RECORD
